cassandra_connector/__init__.py
cassandra_connector/cassandra_connector.py
cassandra_connector/cassandra_connector_manager.py
cassandra_connector-0.3.0.dist-info/LICENSE
cassandra_connector-0.3.0.dist-info/METADATA
cassandra_connector-0.3.0.dist-info/WHEEL
cassandra_connector-0.3.0.dist-info/top_level.txt
cassandra_connector-0.3.0.dist-info/RECORD
