Metadata-Version: 2.1
Name: cassandra-connector
Version: 0.3.0
Summary: Simplifies connecting to Cassandra and AstraDB when using the DataStax driver
Home-page: https://github.com/mieslep/cassandra-connector
Author: Phil Miesle
Author-email: phil.miesle@datastax.com
Keywords: cassandra astra db connector
Classifier: Programming Language :: Python :: 3
Classifier: License :: OSI Approved :: MIT License
Classifier: Operating System :: OS Independent
Requires-Python: >=3.8
License-File: LICENSE
Requires-Dist: cassandra-driver >=3.29.1
Requires-Dist: requests >=2.25.1
